{
    "__articles": "6;6-1;13;29;29-3;34;35;35-1;41",
    "__conclusion": "Violation of Art. 6-1;Remainder inadmissible;Non-pecuniary damage - financial award;Costs and expenses partial award - Convention proceedings",
    "applicability": "",
    "appno": "58174/00",
    "article": [
        "13",
        "34",
        "29",
        "35",
        "6",
        "41"
    ],
    "conclusion": [
        {
            "article": "6-1",
            "base_article": "6",
            "element": "Violation of Art. 6-1",
            "type": "violation"
        },
        {
            "element": "Remainder inadmissible",
            "type": "other"
        },
        {
            "element": "Non-pecuniary damage - financial award",
            "type": "other"
        },
        {
            "element": "Costs and expenses partial award - Convention proceedings",
            "type": "other"
        }
    ],
    "content": {
        "001-76764.docx": [
            {
                "content": "PROCEDURE",
                "elements": [
                    {
                        "content": "1.\u00a0\u00a0The case originated in an application (no. 58174/00) against the  lodged with the Court under Article 34 of the Convention for the Protection of Human Rights and Fundamental Freedoms (\u201cthe Convention\u201d) by a Slovakian national, Mrs Ingrid Ri\u0161kov\u00e1 (\u201cthe applicant\u201d), on 23 January 1999.",
                        "elements": []
                    },
                    {
                        "content": "2.\u00a0\u00a0The applicant, who had been granted legal aid on 30 March 2005, was represented by Mr M. Benedik, a lawyer practising in . The Government of the  (\u201cthe Government\u201d) were represented by their Agent, Mrs A. Pol\u00e1\u010dkov\u00e1.",
                        "elements": []
                    },
                    {
                        "content": "3.\u00a0\u00a0On 24 September 2004 the Court decided to communicate the application. Applying Article 29 \u00a7 3 of the Convention, it decided to rule on the admissibility and merits of the application at the same time.",
                        "elements": []
                    }
                ],
                "section_name": "procedure"
            },
            {
                "content": "THE FACTS",
                "elements": [
                    {
                        "content": "THE CIRCUMSTANCES OF THE CASE",
                        "elements": [
                            {
                                "content": "4.\u00a0\u00a0The applicant was born in 1965 and lives in Trnava.",
                                "elements": []
                            },
                            {
                                "content": "1.\u00a0\u00a0Proceedings concerning the dissolution of co-ownership of a real estate (Trnava District Court file 17C 66/91)",
                                "elements": [
                                    {
                                        "content": "5.\u00a0\u00a0The applicant is the defendant in civil proceedings concerning the dissolution of co-ownership of a real estate. The proceedings were instituted before the Trnava District Court on 27 March 1991.",
                                        "elements": []
                                    },
                                    {
                                        "content": "6.\u00a0\u00a0In the course of 1991 four hearings were scheduled in the case.",
                                        "elements": []
                                    },
                                    {
                                        "content": "7.\u00a0\u00a0On 14 February 1992 an expert opinion was submitted and on 4\u00a0March\u00a01992 the District Court asked a different expert to submit an opinion. On 10\u00a0November 1993 a third expert was asked to submit an opinion.",
                                        "elements": []
                                    },
                                    {
                                        "content": "8.\u00a0\u00a0Between 17 December 1992 and 11 March 1993 the  dealt with the applicant\u2019s appeal against the decision on an advance on experts\u2019 costs.",
                                        "elements": []
                                    },
                                    {
                                        "content": "9.\u00a0\u00a0The third expert\u2019s opinion was served on the parties on 15\u00a0February\u00a01993.",
                                        "elements": []
                                    },
                                    {
                                        "content": "10.\u00a0\u00a0Three hearings were held between March and July 1993. During the same period the second expert was asked for an opinion. It was submitted on 31 May 1993. On 30 March 1993 the applicant appealed against the decision on experts\u2019 fees.",
                                        "elements": []
                                    },
                                    {
                                        "content": "11.\u00a0\u00a0On 5 August 1993 the second and third experts were heard.",
                                        "elements": []
                                    },
                                    {
                                        "content": "12.\u00a0\u00a0A hearing was held on 11 October 1993.",
                                        "elements": []
                                    },
                                    {
                                        "content": "13.\u00a0\u00a0On 13 October 1993 the District Court exempted the applicant from the obligation to pay fees.",
                                        "elements": []
                                    },
                                    {
                                        "content": "14.\u00a0\u00a0On 18 March 1994 the third expert submitted a further opinion at the District Court\u2019s request of 16 December 1993.",
                                        "elements": []
                                    },
                                    {
                                        "content": "15.\u00a0\u00a0Two hearings were held in May 1994.",
                                        "elements": []
                                    },
                                    {
                                        "content": "16.\u00a0\u00a0On 22 July 1994 an administrative authority submitted its opinion on possible distribution of the real estate.",
                                        "elements": []
                                    },
                                    {
                                        "content": "17.\u00a0\u00a0The District Court heard the parties on 17 October 1994. On 17\u00a0November 1994 it delivered a judgment by which it dissolved the joint ownership of the estate and distributed it between the owners.",
                                        "elements": []
                                    },
                                    {
                                        "content": "18.\u00a0\u00a0On 20 April 1995 the appellate court quashed the judgment following the applicant\u2019s appeal.",
                                        "elements": []
                                    },
                                    {
                                        "content": "19.\u00a0\u00a0Hearings before the District Court were scheduled for 18 October 1995 and 20 November 1995. The applicant and the expert did not appear at the former hearing. Another hearing was held on 13 December 1995.",
                                        "elements": []
                                    },
                                    {
                                        "content": "20.\u00a0\u00a0On 12 February 1996 the file was submitted to the  as the applicant had challenged the Trnava District Court judge dealing with the case.",
                                        "elements": []
                                    },
                                    {
                                        "content": "21.\u00a0\u00a0The file was returned to the District Court on 4 March 1996 after the  had decided that the judge was not biased.",
                                        "elements": []
                                    },
                                    {
                                        "content": "22.\u00a0\u00a0On 12 June 1996 the District Court dismissed the applicant\u2019s request for exemption from the obligation to pay the court fees. On 31\u00a0October\u00a01996 the  overturned this decision.",
                                        "elements": []
                                    },
                                    {
                                        "content": "23.\u00a0\u00a0On 4 April 1997 an inspection of the property in question took place in the presence of the parties.",
                                        "elements": []
                                    },
                                    {
                                        "content": "24.\u00a0\u00a0On 17 June 1997 the District Court heard the parties. It decided to revisit the site in the presence of the expert, the representative of the competent authority and the parties.",
                                        "elements": []
                                    },
                                    {
                                        "content": "25.\u00a0\u00a0On 25 September 1997 the judge and the parties re-visited the site.",
                                        "elements": []
                                    },
                                    {
                                        "content": "26.\u00a0\u00a0On 30 September 1997 the District Court heard the plaintiff. It issued an interim measure prohibiting the plaintiff from re-constructing the property. On 29 May 1998 the  modified this decision.",
                                        "elements": []
                                    },
                                    {
                                        "content": "27.\u00a0\u00a0On 22 September 1998 the District Court stayed the proceedings pending the outcome of proceedings in which the marital property of the plaintiffs was to be distributed. On 26 February 1999 the  upheld this decision.",
                                        "elements": []
                                    },
                                    {
                                        "content": "28.\u00a0\u00a0The marital property of the plaintiffs was distributed by a judgment of 2\u00a0July\u00a01999 which became final on 8 March 2001. According to the judgment, each of the plaintiffs owned one half of the relevant real property.",
                                        "elements": []
                                    },
                                    {
                                        "content": "29.\u00a0\u00a0On 2 July 2001 the Trnava District Court decided that the proceedings in issue were to be resumed as from 8 March 2001.",
                                        "elements": []
                                    },
                                    {
                                        "content": "30.\u00a0\u00a0On 2 October 2001 the case was adjourned.",
                                        "elements": []
                                    },
                                    {
                                        "content": "31.\u00a0\u00a0On 19 November 2001 one of the plaintiffs informed the District Court that he wished to withdraw his action. In November and December 2001 the District Court tried to establish the whereabouts of that plaintiff.",
                                        "elements": []
                                    },
                                    {
                                        "content": "32.\u00a0\u00a0On 1 March 2002 the other plaintiff informed the District Court that she wished to withdraw the action. On 12 March 2002 the applicant stated that she did not agree to withdrawal of the action and requested that the merits of the case be determined.",
                                        "elements": []
                                    },
                                    {
                                        "content": "33.\u00a0\u00a0On 14 March 2002 the applicant requested that the case be transferred to a different court. The file was submitted to the  on 7\u00a0June\u00a02002. On 31 July 2002 it returned the case to the District Court as the applicant\u2019s request was not sufficiently specific. On 1 August and on 26\u00a0September 2002 the District Court asked the applicant to substantiate her request. On 1 October 2002 the applicant was asked to pay a fee. On 9\u00a0October 2002 the applicant withdrew her request and the  in Trnava discontinued the proceedings related to it on 8 October 2003.",
                                        "elements": []
                                    },
                                    {
                                        "content": "34.\u00a0\u00a0On 8 January 2004 the District Court obtained information about the address of one of the plaintiffs.",
                                        "elements": []
                                    },
                                    {
                                        "content": "35.\u00a0\u00a0A hearing was scheduled for 28 June 2004. One of the plaintiffs excused herself from the hearing and informed the court that she did not wish to pursue the case.",
                                        "elements": []
                                    },
                                    {
                                        "content": "36.\u00a0\u00a0On 7 September 2004 the District Court discontinued the proceedings as both plaintiffs had withdrawn their claims.",
                                        "elements": []
                                    },
                                    {
                                        "content": "37.\u00a0\u00a0On 23 September 2004 the applicant appealed and requested that the point in issue be determined. On 5 November 2004 she submitted further reasons for her appeal.",
                                        "elements": []
                                    },
                                    {
                                        "content": "38.\u00a0\u00a0On 29 April 2005 the  in Trnava upheld the decision to discontinue the proceedings on the merits. It quashed the first-instance decision on the costs of the proceedings and returned the relevant part of the case to the District Court.",
                                        "elements": []
                                    },
                                    {
                                        "content": "39.\u00a0\u00a0On 26 August 2005 the applicant filed an appeal on points of law against the \u2019s decision.",
                                        "elements": []
                                    },
                                    {
                                        "content": "40.\u00a0\u00a0On 2 November 2005 the District Court exempted the applicant from the obligation to pay the cassation fee.",
                                        "elements": []
                                    },
                                    {
                                        "content": "41.\u00a0\u00a0On 16 December 2005 the file was submitted to the Supreme Court for a decision on the applicant\u2019s appeal on points of law.",
                                        "elements": []
                                    },
                                    {
                                        "content": "42.\u00a0\u00a0The proceedings are pending.",
                                        "elements": []
                                    }
                                ]
                            },
                            {
                                "content": "2.\u00a0\u00a0Proceedings concerning the applicant\u2019s claim of 20 November 1995 (Trnava District Court file 12C 198/95)",
                                "elements": [
                                    {
                                        "content": "43.\u00a0\u00a0On 20 November 1995 the applicant claimed a sum of money from an individual before the Trnava District Court.",
                                        "elements": []
                                    },
                                    {
                                        "content": "44.\u00a0\u00a0On 4 December 1995 the applicant informed the District Court that the defendant had paid a part of the sum due.",
                                        "elements": []
                                    },
                                    {
                                        "content": "45.\u00a0\u00a0Five hearings were scheduled between January and May 1996.",
                                        "elements": []
                                    },
                                    {
                                        "content": "46.\u00a0\u00a0Another two hearings were held on 15 November and on 17\u00a0December\u00a01996.",
                                        "elements": []
                                    },
                                    {
                                        "content": "47.\u00a0\u00a0In April 1997 the case was assigned to a different judge.",
                                        "elements": []
                                    },
                                    {
                                        "content": "48.\u00a0\u00a0On 21 July 1997 the District Court asked the parties to submit comments on documentary evidence. The applicant replied on 1 August 1997. The mail, including a reminder, addressed to the defendant was returned to the court.",
                                        "elements": []
                                    },
                                    {
                                        "content": "49.\u00a0\u00a0On 1 December 1997 and on 7 January 1999 the case was adjourned as the defendant had refused to receive the summons. The police informed the court that the defendant did not live at the addresses indicated by the court.",
                                        "elements": []
                                    },
                                    {
                                        "content": "50.\u00a0\u00a0On 8 February 1999 the Central Population Registry informed the District Court of the defendant\u2019s permanent address.",
                                        "elements": []
                                    },
                                    {
                                        "content": "51.\u00a0\u00a0On 25 May 1999 the court accepted a modification of the applicant\u2019s claim. The defendant challenged the judge. The case was therefore adjourned and the file was transmitted to the  on 1 June 1999.",
                                        "elements": []
                                    },
                                    {
                                        "content": "52.\u00a0\u00a0On 29 July 1999 the  found that the District Court judge was not biased. The file was returned to the District Court on 8\u00a0September\u00a01999. The District Court sent the decision to the parties on 1\u00a0February\u00a02000. As the mail sent to the defendant was returned to the court, it requested the police to serve it on him. On 11 August 2000 the District Court again sent the \u2019s decision of 29 July 1999 to the defendant. On\u00a05\u00a0November\u00a02000 the District Court judge made a note that the mail sent to the defendant had neither been served nor returned to the court. The mail was returned, undelivered, on 15 November 2000.",
                                        "elements": []
                                    },
                                    {
                                        "content": "53.\u00a0\u00a0On 30 October 2000 the case was assigned to a different judge.",
                                        "elements": []
                                    },
                                    {
                                        "content": "54.\u00a0\u00a0On 5 December 2000 the District Court again asked the police to serve the above decision on the defendant. It also asked the Trnava Town Office to inform it of the defendant\u2019s address. The Town Office replied on 29\u00a0December 2000. On 2 January 2001 the police informed the District Court that it was impossible to serve the decision on the defendant. On\u00a026\u00a0March 2001 the District Court again asked the police to serve the document on the defendant. On 26 April 2001 the police informed the court that they could not reach the defendant.",
                                        "elements": []
                                    },
                                    {
                                        "content": "55.\u00a0\u00a0On 1 August 2001 a different judge was assigned to deal with the case. The judge received the file on 6 September 2001.",
                                        "elements": []
                                    },
                                    {
                                        "content": "56.\u00a0\u00a0On 13 November 2002 the case was adjourned because of the absence of the defendant. On the same day the applicant informed the court that the defendant had paid the remainder of the sum due. She modified her claim in that she claimed default interest on the sum in question and reimbursement of her costs.",
                                        "elements": []
                                    },
                                    {
                                        "content": "57.\u00a0\u00a0On 25 November and on 2 December 2002 the authorities concerned informed the District Court of the addresses at which the defendant was registered.",
                                        "elements": []
                                    },
                                    {
                                        "content": "58.\u00a0\u00a0On 27 June 2003 the District Court heard the parties. On 4 July 2003 the applicant specified her outstanding claim at the court\u2019s request.",
                                        "elements": []
                                    },
                                    {
                                        "content": "59.\u00a0\u00a0On 9 December 2003 the applicant extended her claim in that she claimed an additional sum from the defendant.",
                                        "elements": []
                                    },
                                    {
                                        "content": "60.\u00a0\u00a0On 10 December 2003 the District Court held a hearing at which the defendant failed to appear. It invited the applicant to file her additional claim in accordance with the formal requirements. The applicant replied. On 27 February 2004 she made a new submission in respect of the relevant part of the claim at the court\u2019s request of 7 January 2004.",
                                        "elements": []
                                    },
                                    {
                                        "content": "61.\u00a0\u00a0On 13 May 2004 the applicant complained to the President of the District Court that the case had not been proceeded with despite the \u2019s order of 27 October 2003 (see paragraph 74 below). On 28 June 2004 the vice-president of the District Court dismissed the complaint as being manifestly ill-founded.",
                                        "elements": []
                                    },
                                    {
                                        "content": "62.\u00a0\u00a0On 9 September 2004 the applicant asked the District Court to indicate the shortcomings which had to be rectified in her action.",
                                        "elements": []
                                    },
                                    {
                                        "content": "63.\u00a0\u00a0On 16 September 2004 the District Court issued a decision requesting the applicant to eliminate a number of specific shortcomings in her claim within 10 days. That decision was served on the applicant on 4\u00a0January 2005.",
                                        "elements": []
                                    },
                                    {
                                        "content": "64.\u00a0\u00a0On 13 January 2005 the applicant informed the District Court that she wished to withdraw her claim for payment of the debt and the additional sum and that she only requested that the defendant be ordered to reimburse her costs and expenses.",
                                        "elements": []
                                    },
                                    {
                                        "content": "65.\u00a0\u00a0On 16 September 2005 the defendant submitted comments on the case.",
                                        "elements": []
                                    },
                                    {
                                        "content": "66.\u00a0\u00a0On 7 December 2005 the District Court held a hearing. It invited the applicant to specify the sums which she had obtained from the defendant. On 30 December 2005 the applicant replied that she had already submitted that information.",
                                        "elements": []
                                    },
                                    {
                                        "content": "67.\u00a0\u00a0The proceedings are pending.",
                                        "elements": []
                                    }
                                ]
                            },
                            {
                                "content": "3.\u00a0\u00a0Proceedings before the ",
                                "elements": []
                            },
                            {
                                "content": "(a)\u00a0\u00a0Complaint about the proceedings concerning the dissolution of coownership",
                                "elements": [
                                    {
                                        "content": "68.\u00a0\u00a0On 16 December 2002 the applicant complained to the  about the length of the proceedings concerning the dissolution of co-ownership of a real estate. She indicated that the District Court in Trnava was the authority responsible for the alleged violation. The applicant claimed, inter alia, just satisfaction of 130,000 Slovakian korunas (SKK). She later increased this sum to SKK 34 million.",
                                        "elements": []
                                    },
                                    {
                                        "content": "69.\u00a0\u00a0On 27 October 2003 the  found a violation of the applicant\u2019s constitutional right to a hearing without undue delay. It ordered the Trnava District Court to proceed with the case expeditiously. The  further awarded SKK 20,000 as just satisfaction to the applicant.",
                                        "elements": []
                                    },
                                    {
                                        "content": "70.\u00a0\u00a0In its finding the  stated that it only had regard to the length of the proceedings after 15 February 1993 when the Constitutional Court Act came into effect.",
                                        "elements": []
                                    },
                                    {
                                        "content": "71.\u00a0\u00a0The  admitted that the overall length of the period under consideration was partly due to the factual complexity of the case. In its view, the applicant had contributed substantially to the length of the proceedings by her procedural motions, such as appeals against procedural decisions, requests for exemption from the obligation to pay the fees, comments on questions put to experts and by challenging the District Court judges.",
                                        "elements": []
                                    },
                                    {
                                        "content": "72.\u00a0\u00a0As regards the conduct of the District Court, the  noted that the period under consideration lasted more than ten years and that during that time the District Court had held seventeen hearings. Even taking into account that the proceedings had been stayed for two years and five months pending the outcome of a different set of proceedings, their overall length was not reasonable in the particular circumstances of the case. The  noted, in particular, that undue delays of thirteen and twelve months respectively had occurred between 4 March 1996 and 4\u00a0April\u00a01997 and between 9 October 2002 and 1 October 2003. The decision further stated that the District Court had not proceeded with the case diligently.",
                                        "elements": []
                                    }
                                ]
                            },
                            {
                                "content": "(b)\u00a0\u00a0Complaint about the proceedings concerning the applicant\u2019s claim of 20\u00a0November 1995",
                                "elements": [
                                    {
                                        "content": "73.\u00a0\u00a0On 6 December 2002 the applicant filed a complaint under Article 127 of the Constitution about the length of the proceedings concerning her claim of 20 November 1995. She claimed, inter alia, SKK 2 million in just satisfaction.",
                                        "elements": []
                                    },
                                    {
                                        "content": "74.\u00a0\u00a0On 27 October 2003 the  found that the Trnava District Court had violated the applicant\u2019s constitutional right to a hearing without undue delay. It ordered the Trnava District Court to proceed with the case expeditiously. The  further awarded SKK 10,000 as just satisfaction to the applicant.",
                                        "elements": []
                                    },
                                    {
                                        "content": "75.\u00a0\u00a0The decision stated that the case was not complex. As to the applicant\u2019s conduct, the  noted that the defendant had paid her the remainder of the sum originally due on 27 May 1999 and that she had only informed the District Court of this fact and modified her claim accordingly on 13 November 2002.",
                                        "elements": []
                                    },
                                    {
                                        "content": "76.\u00a0\u00a0The decision further stated that the District Court was responsible for undue delays in the proceedings between 1 December 1997 and 7\u00a0January\u00a01999 and between 6 September 2001 and 13 November 2002.",
                                        "elements": []
                                    },
                                    {
                                        "content": "77.\u00a0\u00a0When awarding just satisfaction to the applicant the  took into account that at that time the proceedings no longer concerned the principal sum originally claimed by the applicant, but only default interest and her costs.",
                                        "elements": []
                                    }
                                ]
                            },
                            {
                                "content": "(c)\u00a0\u00a0Complaint of 3 May 2004",
                                "elements": [
                                    {
                                        "content": "78.\u00a0\u00a0On 3 May 2004 the applicant again complained to the  about the length of the proceedings before the Trnava District Court which had been brought against her in 1991. She alleged that the District Court had failed to proceed with the case in compliance with the \u2019s finding of 27 October 2003.",
                                        "elements": []
                                    },
                                    {
                                        "content": "79.\u00a0\u00a0The  rejected the complaint as being inadmissible on 27 May 2004. The decision stated that less than seven months had lapsed from the delivery of the \u2019s judgment of 27 October 2003.",
                                        "elements": []
                                    }
                                ]
                            },
                            {
                                "content": "(d)\u00a0\u00a0Submissions of 3 and 9 June 2004",
                                "elements": [
                                    {
                                        "content": "80.\u00a0\u00a0In two separate letters addressed to the  and dated 3 June 2004 the applicant complained that the District Court in Trnava had caused further delays in the proceedings concerning her cases. She requested that an advocate be appointed to represent her in the constitutional proceedings.",
                                        "elements": []
                                    },
                                    {
                                        "content": "81.\u00a0\u00a0In the letter concerning the proceedings brought in 1995 the applicant stated that the District Court had also violated her rights under Articles 8 and 12 of the Convention, under Article 1 of Protocol No. 1 and under Articles 2-5 of Protocol No. 7. She submitted no further reasons for that allegation.",
                                        "elements": []
                                    },
                                    {
                                        "content": "82.\u00a0\u00a0On 9 June 2004 the applicant sent a letter to the President of the  requesting that the District Court should proceed with the cases without any further delay.",
                                        "elements": []
                                    }
                                ]
                            }
                        ]
                    }
                ],
                "section_name": "facts"
            },
            {
                "content": "THE LAW",
                "elements": [
                    {
                        "content": "I.\u00a0\u00a0ALLEGED VIOLATION OF ARTICLE 6 \u00a7 1 OF THE CONVENTION",
                        "elements": [
                            {
                                "content": "83.\u00a0\u00a0The applicant complained that the length of the above two sets of proceedings had been incompatible with the \u201creasonable time\u201d requirement, provided in Article 6 \u00a7 1 of the Convention, which reads as follows:",
                                "elements": []
                            },
                            {
                                "content": "\u201cIn the determination of his civil rights and obligations ..., everyone is entitled to a ... hearing within a reasonable time by [a] ... tribunal...\u201d",
                                "elements": []
                            },
                            {
                                "content": "84.\u00a0\u00a0As regards the proceedings concerning the dissolution of the coownership of a real estate brought on 27 March 1991, the period to be taken into consideration only began on 18 March 1992, when the recognition by the former Czech and Slovak Federal Republic, of which Slovakia is one of the successor States, of the right of individual petition took effect. However, in assessing the reasonableness of the time that elapsed after that date, account must be taken of the state of proceedings at the time. That period has not yet ended. It has thus lasted 14 years and more than 3 months for three levels of jurisdiction. The Court has noted that the proceedings were stayed, for 29 months approximately, pending the outcome of proceedings in which the marital property of the plaintiffs had to be distributed.",
                                "elements": []
                            },
                            {
                                "content": "As regards the other set of proceedings, the period to be taken into consideration began on 20 November 1995 and has not yet ended. It has thus lasted 10 years and more than 7 months during which the merits of the case have been examined at a single level of jurisdiction.",
                                "elements": []
                            },
                            {
                                "content": "A.\u00a0\u00a0Admissibility",
                                "elements": [
                                    {
                                        "content": "85.\u00a0\u00a0The Government, with reference to the \u2019s judgments of 27 October 2003, argued that the applicant could no longer claim to be a victim, within the meaning of Article 34 of the Convention, in respect of any delays in the proceedings covered by those judgments. They argued that the just satisfaction awarded by the  was not disproportionately low in the particular circumstances. In addition, the  had ordered the District Court to proceed with the cases without any further delay.",
                                        "elements": []
                                    },
                                    {
                                        "content": "86.\u00a0\u00a0In the Government\u2019s view, no further delays arose in the proceedings before the District Court following the delivery of the above judgments of the . In any event, the applicant should have sought redress by means of fresh complaints under Article 127 of the Constitution.",
                                        "elements": []
                                    },
                                    {
                                        "content": "87.\u00a0\u00a0The applicant disagreed. She submitted that the just satisfaction awarded to her by the  in respect of both sets of proceedings was unreasonably low and that the Trnava District Court had failed to proceed with her cases speedily after the delivery of the \u2019s judgments of 27 October 2003.",
                                        "elements": []
                                    },
                                    {
                                        "content": "88.\u00a0\u00a0The question whether the applicant can still claim to be a \u201cvictim\u201d, within the meaning of Article 34 of the Convention, of a violation of her right to a\u00a0hearing within a reasonable time falls to be determined in the light of the principles recently established under the Court\u2019s case-law (Cocchiarella v. Italy [GC], no.\u00a064886/01, \u00a7\u00a7 69-107, ECHR 2006... and Scordino v. Italy (no. 1) [GC], no.\u00a036813/97, \u00a7\u00a7 178-213, ECHR 2006 - ...).",
                                        "elements": []
                                    },
                                    {
                                        "content": "89.\u00a0\u00a0The Constitutional Court, after having analysed the two sets of proceedings complained of in the light of the criteria which the Court also applies, awarded the applicant the equivalent of 500 euros (EUR) in respect of the proceedings brought in 1991 and EUR 250 euros in respect of the proceedings brought in 1995.\u00a0The just satisfaction awarded by the  amounts to approximately 10 and 5 per cent respectively of what the Court would be likely to award the applicant, at that time, in accordance with its practice taking into account the particular circumstances of the two sets of proceedings in issue. This factor alone leads to the conclusion that the redress provided to the applicant at domestic level, considered on the basis of the facts about which she complains before the Court, was insufficient. In these circumstances, the argument that the applicant has lost her status as a \u201cvictim\u201d cannot be upheld.",
                                        "elements": []
                                    },
                                    {
                                        "content": "90.\u00a0\u00a0The  explicitly ordered the District Court in Trnava to proceed with the applicant\u2019s cases without any further delay. In these circumstances, the applicant was not required, for the purpose of Article 35 \u00a7 1 of the Convention, to file fresh constitutional complaints if she was of the opinion that the District Court had failed to comply with those orders.",
                                        "elements": []
                                    },
                                    {
                                        "content": "The Court further notes that it was open to the applicant to seek redress by means of the remedy under Article 127 of the Constitution to the extent that she may be understood as complaining also about delays in the proceedings before the Regional Court and the Supreme Court after the delivery of the Constitutional Court\u2019s judgments of 27 October 2003. The applicant has not done so, and this fact has to be taken into account when determining the merits of this part of the application and, if appropriate, the applicant\u2019s claims for just satisfaction under Article 41 of the Convention.",
                                        "elements": []
                                    },
                                    {
                                        "content": "91.\u00a0\u00a0The complaint about the length of the two sets of proceedings in issue is not manifestly ill-founded within the meaning of Article 35 \u00a7 3 of the Convention. It is not inadmissible on any other grounds. It must therefore be declared admissible.",
                                        "elements": []
                                    }
                                ]
                            },
                            {
                                "content": "B.\u00a0\u00a0Merits",
                                "elements": [
                                    {
                                        "content": "92.\u00a0\u00a0The Government referred to the \u2019s judgments given on 27 October 2003 and admitted that the applicant\u2019s right to a hearing within a reasonable time had been violated in both sets of proceedings.",
                                        "elements": []
                                    },
                                    {
                                        "content": "93.\u00a0\u00a0The applicant maintained that the  had not taken into account all delays which had occurred in the course of the proceedings. Furthermore, the District Court had not respected the order of the . In particular, as regards the proceedings brought in 1995, the District Court had taken more than 9 months to clearly specify, in the decision of 16 September 2004, the shortcomings which the applicant was required to eliminate in her submissions. The District Court had not subsequently proceeded with the case diligently.",
                                        "elements": []
                                    },
                                    {
                                        "content": "94.\u00a0\u00a0The Court reiterates that the reasonableness of the length of proceedings must be assessed in the light of the circumstances of the case and with reference to the following criteria: the complexity of the case, the conduct of the applicant and the relevant authorities and what was at stake for the applicant in the dispute (see, among many other authorities, Frydlender v. France [GC], no. 30979/96, \u00a7 43, ECHR 2000-VII).",
                                        "elements": []
                                    },
                                    {
                                        "content": "95.\u00a0\u00a0Having examined all the material submitted to it, and having regard to its case-law on the subject, the Court concurs with the findings of the Constitutional Court that the length of both sets of proceedings complained of was excessive and failed to meet the \u201creasonable time\u201d requirement.",
                                        "elements": []
                                    },
                                    {
                                        "content": "96.\u00a0\u00a0As regards the period subsequent to the delivery of the \u2019s judgments, the Court, given the lengthy intervals between the various individual procedural steps, shares the applicant\u2019s view that further unjustified delays occurred in the course of 2004 and 2005 in the proceedings before the District Court on the action initiated in 1995.",
                                        "elements": []
                                    },
                                    {
                                        "content": "As regards the proceedings brought in 1991, the Court notes that the District Court scheduled a hearing more than 5 months after it had identified the address of one of the plaintiffs. The Court would not attach particular importance to this fact as the District Court discontinued the proceedings on 7 September 2004, that is less than one year after the delivery of the \u2019s finding. Subsequently, the court of appeal and the court of cassation dealt with the case at the applicant\u2019s request.",
                                        "elements": []
                                    },
                                    {
                                        "content": "97.\u00a0\u00a0In view of the above considerations, the Court concludes that there has been a breach of Article 6 \u00a7 1 in respect of the length of the two sets of proceedings in issue.",
                                        "elements": []
                                    }
                                ]
                            }
                        ]
                    },
                    {
                        "content": "II.\u00a0\u00a0ALLEGED VIOLATION OF ARTICLE 13 OF THE CONVENTION",
                        "elements": [
                            {
                                "content": "98.\u00a0\u00a0The applicant further complained that she had no effective remedy at her disposal as regards the alleged violation of her right to a hearing within a reasonable time. She relied on Article 13 of the Convention.",
                                "elements": []
                            },
                            {
                                "content": "99.\u00a0\u00a0The Government contested that argument.",
                                "elements": []
                            },
                            {
                                "content": "100.\u00a0\u00a0As from 1 January 2002 it has been open to the applicant to complain under Article 127 of the Constitution about unjustified delays in the proceedings. The applicant had recourse to that remedy and the  found that her right to a hearing within a reasonable time had been violated in both sets of proceedings. It provided redress of both a compensatory and preventative nature to her. The applicant thus had an effective remedy at her disposal as required by Article 13. The fact that the just satisfaction awarded by the  does not coincide with the awards of the Court in comparable cases or that, as the applicant alleges, further delays occurred after the delivery of the \u2019s judgments of 27 October 2003, cannot affect the position.",
                                "elements": []
                            },
                            {
                                "content": "101.\u00a0\u00a0It follows that this complaint is manifestly ill-founded and must be rejected in accordance with Article\u00a035 \u00a7\u00a7\u00a03 and\u00a04 of the Convention.",
                                "elements": []
                            }
                        ]
                    },
                    {
                        "content": "III.\u00a0\u00a0ALLEGED VIOLATION OF ARTICLES 1, 3, 5, 8, 12 AND 14 OF THE CONVENTION, OF ARTICLE 1 OF PROTOCOL No. 1, OF ARTICLES 2-4 OF PROTOCOL No. 4 AND OF ARTICLES 2-5 OF PROTOCOL No. 7",
                        "elements": [
                            {
                                "content": "102.\u00a0\u00a0The applicant complained under Articles 3 and 14 of the Convention that by its conduct in her cases the Trnava District Court subjected her to degrading and discriminatory treatment. She further alleged that the facts of the case also amounted to a violation of her rights under Articles 1, 5, 8 and 12 of the Convention, under Article 1 of Protocol No. 1, under Articles 2 to 4 of Protocol No. 4 and under Articles 2 to 5 of Protocol No. 7.",
                                "elements": []
                            },
                            {
                                "content": "103.\u00a0\u00a0The Government objected that the applicant had not exhausted domestic remedies as she failed to seek redress in due form before the domestic authorities including, ultimately, the . As regards the complaint under Article 1 of Protocol No. 1 in particular, they expressed doubt about whether the applicant\u2019s submissions of 3 and 9 June 2004 had reached the  and whether they met the formal requirements for new proceedings to be brought before the .",
                                "elements": []
                            },
                            {
                                "content": "104.\u00a0\u00a0The Court notes that in her letter to the Constitutional Court of 3\u00a0June 2004 concerning the proceedings brought in 1995 the applicant invoked several provisions of the Convention, including Article 1 of Protocol No. 1, without giving further reasons. Even assuming that domestic remedies were exhausted, the Court finds that the above complaints, to the extent that they have been substantiated and fall within its competence, disclose no appearance of a violation of the Convention or its Protocols.",
                                "elements": []
                            },
                            {
                                "content": "105.\u00a0\u00a0It follows that this part of the application is manifestly ill-founded and must be rejected in accordance with Article\u00a035 \u00a7\u00a7\u00a03 and\u00a04 of the Convention.",
                                "elements": []
                            }
                        ]
                    },
                    {
                        "content": "IV.\u00a0\u00a0APPLICATION OF ARTICLE 41 OF THE CONVENTION",
                        "elements": [
                            {
                                "content": "106.\u00a0\u00a0Article 41 of the Convention provides:",
                                "elements": []
                            },
                            {
                                "content": "\u201cIf the Court finds that there has been a violation of the Convention or the Protocols thereto, and if the internal law of the High Contracting Party concerned allows only partial reparation to be made, the Court shall, if necessary, afford just satisfaction to the injured party.\u201d",
                                "elements": []
                            },
                            {
                                "content": "A.\u00a0\u00a0Damage",
                                "elements": [
                                    {
                                        "content": "107.\u00a0\u00a0The applicant claimed SKK 3 million in respect of non-pecuniary damage.",
                                        "elements": []
                                    },
                                    {
                                        "content": "108.\u00a0\u00a0The Government contested the claim.",
                                        "elements": []
                                    },
                                    {
                                        "content": "109.\u00a0\u00a0The Court recalls that, where an applicant can still claim to be a \u201cvictim\u201d after exhausting the domestic remedy available, he or she must be awarded the difference between the amount obtained in domestic proceedings and an amount that would not have been regarded as manifestly unreasonable compared with the amount awarded by the Court if it had been awarded by the competent domestic authority.\u00a0Applicants should also be awarded an amount in respect of stages of the proceedings that may not have been taken into account by the competent domestic authority (see the Cocchiarella v. Italy [GC] judgment referred to above, \u00a7\u00a7 139-141).",
                                        "elements": []
                                    },
                                    {
                                        "content": "110.\u00a0\u00a0The Court finds that on the basis of the circumstances of the present case it would have awarded, in the absence of domestic remedies and at the time when the \u2019s decisions were given, the sum of EUR\u00a05,000 in respect of each of the two sets of proceedings complained of. It notes that the applicant was awarded EUR 500 and EUR 250 respectively which is 10 and 5% of what the Court would have awarded.",
                                        "elements": []
                                    },
                                    {
                                        "content": "Having regard to the characteristics of the constitutional remedy chosen in  and the fact that, notwithstanding this national remedy, the Court has found a violation, it considers, ruling on an equitable basis, that the applicant should be awarded the total sum of EUR\u00a03,750 in respect of the two sets of proceedings.",
                                        "elements": []
                                    },
                                    {
                                        "content": "The Court also awards EUR 1,000 for the further delay suffered by the applicant in the proceedings before the District Court concerning her action of 1995.",
                                        "elements": []
                                    },
                                    {
                                        "content": "111.\u00a0\u00a0Accordingly, the applicant is entitled to compensation for nonpecuniary damage in the sum of EUR 4,750, plus any tax that may be chargeable on that amount.",
                                        "elements": []
                                    }
                                ]
                            },
                            {
                                "content": "B.\u00a0\u00a0Costs and expenses",
                                "elements": [
                                    {
                                        "content": "112.\u00a0\u00a0The applicant also claimed SKK 7,400 (approximately 200 euros) for the costs and expenses incurred before the Court.",
                                        "elements": []
                                    },
                                    {
                                        "content": "113.\u00a0\u00a0The Government contested the claim arguing that any compensation awarded by the Court should exclusively concern the reasonably incurred costs and expenses.",
                                        "elements": []
                                    },
                                    {
                                        "content": "114.\u00a0\u00a0According to the Court\u2019s case-law, an applicant is entitled to reimbursement of his or her costs and expenses only in so far as it has been shown that these have been actually and necessarily incurred and were reasonable as to quantum. In the present case, the President of the Chamber decided, on 30 March 2005, that legal aid should be granted to the applicant. The applicant appointed a lawyer to represent her in the proceedings before the Court, under the legal aid scheme of the Council of Europe, on 12\u00a0June\u00a02005.",
                                        "elements": []
                                    },
                                    {
                                        "content": "In these circumstances, the Court considers it reasonable to award the sum of EUR 100 in respect of postage, photocopying and other outofpocket expenses which the applicant incurred in the context of the proceedings before the Court prior to the decision to grant legal aid to her.",
                                        "elements": []
                                    }
                                ]
                            },
                            {
                                "content": "C.\u00a0\u00a0Default interest",
                                "elements": [
                                    {
                                        "content": "115.\u00a0\u00a0The Court considers it appropriate that the default interest should be based on the marginal lending rate of the European Central Bank, to which should be added three percentage points.",
                                        "elements": []
                                    }
                                ]
                            }
                        ]
                    }
                ],
                "section_name": "law"
            },
            {
                "content": "FOR THESE REASONS, THE COURT",
                "elements": [
                    {
                        "content": "1.\u00a0\u00a0Declares unanimously the complaint under Article 6 \u00a7 1 of the Convention concerning the excessive length of the two sets of proceedings in issue admissible and the remainder of the application inadmissible;",
                        "elements": []
                    },
                    {
                        "content": "2.\u00a0\u00a0Holds unanimously that there has been a violation of Article 6 \u00a7 1 of the Convention as a result of the length of both sets of proceedings;",
                        "elements": []
                    },
                    {
                        "content": "3.\u00a0\u00a0Holds by five votes to two",
                        "elements": []
                    },
                    {
                        "content": "(a)\u00a0\u00a0that the respondent State is to pay the applicant, within three months from the date on which the judgment becomes final in accordance with Article\u00a044\u00a0\u00a7\u00a02 of the Convention, EUR 4,750 (four thousand seven hundred and fifty euros) in respect of non-pecuniary damage and EUR 100 (one hundred euros) in respect of costs and expenses, the above amounts to be converted into the currency of the respondent State at the rate applicable at the date of settlement, plus any tax that may be chargeable;",
                        "elements": []
                    },
                    {
                        "content": "(b)\u00a0\u00a0that from the expiry of the above-mentioned three months until settlement simple interest shall be payable on the above amounts at a rate equal to the marginal lending rate of the European Central Bank during the default period plus three percentage points;",
                        "elements": []
                    },
                    {
                        "content": "4.\u00a0\u00a0Dismisses by five votes to two the remainder of the applicant\u2019s claim for just satisfaction.",
                        "elements": []
                    },
                    {
                        "content": "Done in English, and notified in writing on 22 August 2006, pursuant to Rule 77 \u00a7\u00a7 2 and 3 of the Rules of Court.",
                        "elements": []
                    },
                    {
                        "content": "In accordance with Article 45 \u00a7 2 of the Convention and Rule 74 \u00a7 2 of the Rules of Court, the partly dissenting opinion of Mr Casadevall and Mr\u00a0Bonello is annexed to this judgment.",
                        "elements": []
                    },
                    {
                        "content": "1.\u00a0\u00a0We did not vote with the majority on items 3 and 4 of the operational provisions of the judgment because, without any convincing reason being given, the amount awarded for non-pecuniary damage under Article 41 (just satisfaction) was substantially less than it should have been.",
                        "elements": []
                    },
                    {
                        "content": "2.\u00a0\u00a0The applicant had brought two sets of civil proceedings. The first concerned an application to bring a co-ownership arrangement to an end and began on 27 March 1991; the second concerned a claim for a sum of money and began on 20 November 1995. However, even though the applicant has exhausted the available domestic remedies in the , both sets of proceedings are still pending. The question which this raises is whether the remedy provided to deal with length-of-proceedings complaints in Slovakia is (in the light of the principles established by the Kudla v. Poland judgment) effective \u201c... in the sense either of preventing the alleged violation or its continuation, or of providing adequate redress for any violation that had already occurred\u201d. This does not appear to have been the case in this instance, as the proceedings have still not ended and the applicant has received only EUR 750 in compensation.",
                        "elements": []
                    },
                    {
                        "content": "3.\u00a0\u00a0The applicant may, therefore, still claim to be a victim of the alleged violation, as is recognised in paragraph 89 of the judgment. Since she has not, in our view, contributed to the excessive delays in the proceedings, her award of just satisfaction for non-pecuniary damage should have been calculated in accordance with the principles laid down in the recent judgments of Cocchiarella v. Italy and Scordino v. Italy, which, by our reckoning, would have entitled her to the sum of EUR 6,775.",
                        "elements": []
                    }
                ],
                "section_name": "conclusion"
            }
        ]
    },
    "decision_body": [
        {
            "name": "SirNicolas Bratza",
            "role": "president"
        },
        {
            "name": "MrJ. Casadevall",
            "role": "judges"
        },
        {
            "name": "MrG. Bonello",
            "role": "judges"
        },
        {
            "name": "MrM. Pellonp\u00e4\u00e4",
            "role": "judges"
        },
        {
            "name": "MrK. Traja",
            "role": "judges"
        },
        {
            "name": "MrS. Pavlovschi",
            "role": "judges"
        },
        {
            "name": "MrJ. \u0160ikuta",
            "role": "judges"
        },
        {
            "name": "Mr T.L. Early",
            "role": "section registrar"
        }
    ],
    "decisiondate": "11/07/2006 00:00:00",
    "docname": "CASE OF RISKOVA v. SLOVAKIA",
    "doctypebranch": "CHAMBER",
    "documentcollectionid": [
        "CASELAW",
        "JUDGMENTS",
        "CHAMBER",
        "ENG"
    ],
    "documents": [
        "001-76764.docx"
    ],
    "ecli": "ECLI:CE:ECHR:2006:0822JUD005817400",
    "externalsources": [],
    "extractedappno": [
        "58174/00",
        "66/91",
        "198/95",
        "64886/01",
        "36813/97",
        "30979/96"
    ],
    "importance": "4",
    "introductiondate": "23/01/1999 00:00:00",
    "issue": [
        "Article 127 of the Constitution"
    ],
    "itemid": "001-76764",
    "judgementdate": "22/08/2006 00:00:00",
    "kpdate": "22/08/2006 00:00:00",
    "kpthesaurus": [
        "14",
        "128",
        "183",
        "498",
        "445",
        "40",
        "57",
        "444",
        "110",
        "216"
    ],
    "languageisocode": "ENG",
    "originatingbody": "7",
    "paragraphs": [
        "13",
        "34",
        "29",
        "35-1",
        "41",
        "6-1",
        "35",
        "6",
        "29-3"
    ],
    "parties": [
        "RISKOVA",
        "SLOVAKIA"
    ],
    "rank": "555.87353515625",
    "representedby": [
        "BENEDIK M."
    ],
    "respondent": "SVK",
    "respondentOrderEng": "42",
    "scl": [
        "Cocchiarella v. Italy [GC], no. 64886/01, \u00a7\u00a7 69-107, , \u00a7\u00a7 139-141, ECHR 2006-...",
        "Frydlender v. France [GC], no. 30979/96, \u00a7 43, ECHR 2000-VII",
        "Scordino v. Italy (no. 1) [GC], no. 36813/97, \u00a7\u00a7 178-213, ECHR 2006-..."
    ],
    "separateopinion": "TRUE",
    "sharepointid": "339656",
    "typedescription": "15"
}